ficobois
