Metadata-Version: 1.1
Name: ficobois
Version: 0.1.5
Summary: This is a test to see if I can put up a function python package. 
Home-page: https://github.com/piotrsenkow/ficobois
Author: Piotr Senkow
Author-email: piotrsenkow@gmail.com
License: MIT license
Keywords: ficobois
Platform: UNKNOWN
Classifier: Development Status :: 2 - Pre-Alpha
Classifier: Intended Audience :: Developers
Classifier: License :: OSI Approved :: MIT License
Classifier: Natural Language :: English
Classifier: Programming Language :: Python :: 2
Classifier: Programming Language :: Python :: 2.7
Classifier: Programming Language :: Python :: 3
Classifier: Programming Language :: Python :: 3.4
Classifier: Programming Language :: Python :: 3.5
Classifier: Programming Language :: Python :: 3.6
Classifier: Programming Language :: Python :: 3.7
